amlgym
