Metadata-Version: 2.4
Name: amlgym
Version: 1.0.1
Summary: Action model learning benchmarking.
Author: Omar Watted
Author-email: Leonardo Lamanna <llamanna@fbk.eu>
Maintainer-email: Leonardo Lamanna <llamanna@fbk.eu>
License-Expression: MIT
Project-URL: Homepage, https://github.com/LamannaLeonardo/AMLGym
Project-URL: Documentation, https://github.com/LamannaLeonardo/AMLGym
Project-URL: Repository, https://github.com/LamannaLeonardo/AMLGym
Project-URL: Bug Tracker, https://github.com/LamannaLeonardo/AMLGym/issues
Keywords: action model learning,domain model learning,action model acquisition
Classifier: Intended Audience :: Science/Research
Classifier: Programming Language :: Python
Classifier: Topic :: Scientific/Engineering :: Artificial Intelligence
Requires-Python: >=3.8
License-File: LICENSE.md
Requires-Dist: unified-planning>=1.2.0
Requires-Dist: up-fast-downward>=0.4.1
Requires-Dist: tarski>=0.8.2
Requires-Dist: pddl-plus-parser==3.14.7
Requires-Dist: anytree>=2.8.0
Requires-Dist: pddl>=0.4.3
Requires-Dist: pyyaml
Requires-Dist: pandas>=2.2.3
Requires-Dist: alive-progress>=3.2.0
Requires-Dist: matplotlib>=3.10.3
Requires-Dist: scikit-learn>=1.7.2
Requires-Dist: openpyxl>=3.1.5
Requires-Dist: clingo>=5.7.1
Requires-Dist: torch>=2.6.0
Requires-Dist: seaborn>=0.13.0
Requires-Dist: nolam
Requires-Dist: offlam
Dynamic: license-file
